[
  {
    "templateName": "手套武器箱",
    "templateId": "77",
    "iconUrl": "https://youpin.img898.com/csgo/template/20a859d772de40ebb001566045f5416b.png",
    "price": "¥117.47",
    "leasePrice": null,
    "increasePercentage": null,
    "increaseValue": null,
    "leasePercentage": null
  },
  {
    "templateName": "海军上尉里克索尔 | 海军水面战中心海豹部队",
    "templateId": "215",
    "iconUrl": "https://youpin.img898.com/csgo/template/c17e376b5dc042ffa2100a5789381592.png",
    "price": "¥173.49",
    "leasePrice": null,
    "increasePercentage": null,
    "increaseValue": null,
    "leasePercentage": null
  },
  {
    "templateName": "AK-47 | 安全网 (崭新出厂)",
    "templateId": "44220",
    "iconUrl": "https://youpin.img898.com/csgo/template/14270a076ec24e94b6965aa7d57b4354.png",
    "price": "¥264.9",
    "leasePrice": null,
    "increasePercentage": null,
    "increaseValue": null,
    "leasePercentage": null
  },
  {
    "templateName": "MP7 | 渐变之色 (崭新出厂)",
    "templateId": "5473",
    "iconUrl": "https://youpin.img898.com/csgo/template/430da880b09e468abfc6b893bc4ae00c.png",
    "price": "¥257",
    "leasePrice": null,
    "increasePercentage": null,
    "increaseValue": null,
    "leasePercentage": null
  },
  {
    "templateName": "USP 消音版 | 次时代 (崭新出厂)",
    "templateId": "228",
    "iconUrl": "https://youpin.img898.com/csgo/template/5f2f18d9f92348a7bcdb674ebadca2a3.png",
    "price": "¥382.5",
    "leasePrice": null,
    "increasePercentage": null,
    "increaseValue": null,
    "leasePercentage": null
  },
  {
    "templateName": "印花 | IHC Esports（全息）| 2022年里约热内卢锦标赛",
    "templateId": "102958",
    "iconUrl": "https://youpin.img898.com/csgo/template/3bdfa4a7fa9c4f51b497125bb971eff0.png",
    "price": "¥219",
    "leasePrice": null,
    "increasePercentage": null,
    "increaseValue": null,
    "leasePercentage": null
  },
  {
    "templateName": "印花 | G2 Esports（全息）| 2024年上海锦标赛",
    "templateId": "110110",
    "iconUrl": "https://youpin.img898.com/csgo/template/e15846a1c9024c65ac43ce7b1ca6f03d.png",
    "price": "¥516.47",
    "leasePrice": null,
    "increasePercentage": null,
    "increaseValue": null,
    "leasePercentage": null
  },
  {
    "templateName": "迈克·赛弗斯 | 联邦调查局（FBI）狙击手",
    "templateId": "439",
    "iconUrl": "https://youpin.img898.com/csgo/template/88348ba385be4a309b6eef1d5bf12ad8.png",
    "price": "¥113",
    "leasePrice": null,
    "increasePercentage": null,
    "increaseValue": null,
    "leasePercentage": null
  },
  {
    "templateName": "格洛克 18 型 | 核子花园 (崭新出厂)",
    "templateId": "2302",
    "iconUrl": "https://youpin.img898.com/csgo/template/18f26492d7ef41ee8b0ea9cfa8aae27e.png",
    "price": "¥689",
    "leasePrice": null,
    "increasePercentage": null,
    "increaseValue": null,
    "leasePercentage": null
  },
  {
    "templateName": "AWP | 冥界之河 (崭新出厂)",
    "templateId": "47628",
    "iconUrl": "https://youpin.img898.com/csgo/template/02193745172447cb9ad9c835f63f268e.png",
    "price": "¥183",
    "leasePrice": null,
    "increasePercentage": null,
    "increaseValue": null,
    "leasePercentage": null
  },
  {
    "templateName": "“医生”罗曼诺夫 | 军刀",
    "templateId": "822",
    "iconUrl": "https://youpin.img898.com/csgo/template/752a5942a3bd4732b740aa9e8d61d5b4.png",
    "price": "¥104.99",
    "leasePrice": null,
    "increasePercentage": null,
    "increaseValue": null,
    "leasePercentage": null
  },
  {
    "templateName": "R8 左轮手枪 | 渐变琥珀 (崭新出厂)",
    "templateId": "180",
    "iconUrl": "https://youpin.img898.com/csgo/template/6bfda316c3974081b8d9fb0cf49d545e.png",
    "price": "¥110",
    "leasePrice": null,
    "increasePercentage": null,
    "increaseValue": null,
    "leasePercentage": null
  },
  {
    "templateName": "AK-47 | 抽象派 1337 (久经沙场)",
    "templateId": "61401",
    "iconUrl": "https://youpin.img898.com/csgo/template/dc1fad026c824b3994a7ecd74107972e.png",
    "price": "¥1840",
    "leasePrice": null,
    "increasePercentage": null,
    "increaseValue": null,
    "leasePercentage": null
  },
  {
    "templateName": "沙漠之鹰 | 印花集 (久经沙场)",
    "templateId": "1644",
    "iconUrl": "https://youpin.img898.com/csgo/template/96295821382547d0b209e63fbc5084f1.png",
    "price": "¥249.99",
    "leasePrice": null,
    "increasePercentage": null,
    "increaseValue": null,
    "leasePercentage": null
  },
  {
    "templateName": "Tec-9 | 竹林 (崭新出厂)",
    "templateId": "2002",
    "iconUrl": "https://youpin.img898.com/csgo/template/bffa87fc5686406387e9e1dafcbf6157.png",
    "price": "¥423",
    "leasePrice": null,
    "increasePercentage": null,
    "increaseValue": null,
    "leasePercentage": null
  },
  {
    "templateName": "AK-47 | 红线 (久经沙场)",
    "templateId": "1414",
    "iconUrl": "https://youpin.img898.com/csgo/template/b3103b2cbf0047c690397e3111a71e51.png",
    "price": "¥203",
    "leasePrice": null,
    "increasePercentage": null,
    "increaseValue": null,
    "leasePercentage": null
  },
  {
    "templateName": "爱娃特工 | 联邦调查局（FBI）",
    "templateId": "820",
    "iconUrl": "https://youpin.img898.com/csgo/template/38cb6172849c46dcb1c4a78420bb7e7f.png",
    "price": "¥137",
    "leasePrice": null,
    "increasePercentage": null,
    "increaseValue": null,
    "leasePercentage": null
  },
  {
    "templateName": "FN57 | 同步力场 (崭新出厂)",
    "templateId": "61421",
    "iconUrl": "https://youpin.img898.com/csgo/template/6182688126bc40f1a12c00ff55e76e94.png",
    "price": "¥150.4",
    "leasePrice": null,
    "increasePercentage": null,
    "increaseValue": null,
    "leasePercentage": null
  },
  {
    "templateName": "M4A1消音版 | 氮化处理 (崭新出厂)",
    "templateId": "43642",
    "iconUrl": "https://youpin.img898.com/csgo/template/9d7cbfce57674922b350dec09f4a6191.png",
    "price": "¥251",
    "leasePrice": null,
    "increasePercentage": null,
    "increaseValue": null,
    "leasePercentage": null
  },
  {
    "templateName": "AWP | 复古流行 (崭新出厂)",
    "templateId": "61675",
    "iconUrl": "https://youpin.img898.com/csgo/template/70e789c7e6c24cf98b263688924df866.png",
    "price": "¥544.5",
    "leasePrice": null,
    "increasePercentage": null,
    "increaseValue": null,
    "leasePercentage": null
  },
  {
    "templateName": "AWP | 印花集 (久经沙场)",
    "templateId": "110925",
    "iconUrl": "https://youpin.img898.com/csgo/template/f9f45c0288114efc986ad7aa4ddc1bca.png",
    "price": "¥326.29",
    "leasePrice": null,
    "increasePercentage": null,
    "increaseValue": null,
    "leasePercentage": null
  },
  {
    "templateName": "法玛斯 | 机械工业 (崭新出厂)",
    "templateId": "34694",
    "iconUrl": "https://youpin.img898.com/csgo/template/05cd7e67a6b34f838747a6ea587963f1.png",
    "price": "¥1440",
    "leasePrice": null,
    "increasePercentage": null,
    "increaseValue": null,
    "leasePercentage": null
  },
  {
    "templateName": "街头士兵 | 凤凰战士",
    "templateId": "44745",
    "iconUrl": "https://youpin.img898.com/csgo/template/af4b2b806b324d12998199fbae1d2192.png",
    "price": "¥168",
    "leasePrice": null,
    "increasePercentage": null,
    "increaseValue": null,
    "leasePercentage": null
  },
  {
    "templateName": "指挥官 梅 “极寒” 贾米森 | 特警",
    "templateId": "44360",
    "iconUrl": "https://youpin.img898.com/csgo/template/8354b7cd8fea4891aa3776f257d6318e.png",
    "price": "¥170.5",
    "leasePrice": null,
    "increasePercentage": null,
    "increaseValue": null,
    "leasePercentage": null
  },
  {
    "templateName": "MP7 | 卷云 (崭新出厂)",
    "templateId": "544",
    "iconUrl": "https://youpin.img898.com/csgo/template/37dbf4445c154421b94a417871895e7f.png",
    "price": "¥155.99",
    "leasePrice": null,
    "increasePercentage": null,
    "increaseValue": null,
    "leasePercentage": null
  },
  {
    "templateName": "M4A1消音版 | 控制台 (略有磨损)",
    "templateId": "43592",
    "iconUrl": "https://youpin.img898.com/csgo/template/09cfb68aa844443ca97f4a982897b9e5.png",
    "price": "¥330.5",
    "leasePrice": null,
    "increasePercentage": null,
    "increaseValue": null,
    "leasePercentage": null
  },
  {
    "templateName": "沙漠之鹰 | 午夜风暴 (崭新出厂)",
    "templateId": "2180",
    "iconUrl": "https://youpin.img898.com/csgo/template/0b8bae68db364a9f961be179a8877320.png",
    "price": "¥1445.5",
    "leasePrice": null,
    "increasePercentage": null,
    "increaseValue": null,
    "leasePercentage": null
  },
  {
    "templateName": "中尉雷克斯·克里奇 | 海豹蛙人",
    "templateId": "101014",
    "iconUrl": "https://youpin.img898.com/csgo/template/5f70c44446924c59a6ab80cc3c67b28a.png",
    "price": "¥208",
    "leasePrice": null,
    "increasePercentage": null,
    "increaseValue": null,
    "leasePercentage": null
  },
  {
    "templateName": "电竞 2014 夏季武器箱",
    "templateId": "1117",
    "iconUrl": "https://youpin.img898.com/csgo/template/251c602b02d4480bada648360d2ee717.png",
    "price": "¥120.9",
    "leasePrice": null,
    "increasePercentage": null,
    "increaseValue": null,
    "leasePercentage": null
  },
  {
    "templateName": "老K | 专业人士",
    "templateId": "14798",
    "iconUrl": "https://youpin.img898.com/csgo/template/71e59f69541d4dd9909e30277aaf03a5.png",
    "price": "¥334.5",
    "leasePrice": null,
    "increasePercentage": null,
    "increaseValue": null,
    "leasePercentage": null
  },
  {
    "templateName": "AK-47 | 抽象派 1337 (略有磨损)",
    "templateId": "61404",
    "iconUrl": "https://youpin.img898.com/csgo/template/7e0ddf19eb7e438d9c764af556350c36.png",
    "price": "¥2596.5",
    "leasePrice": null,
    "increasePercentage": null,
    "increaseValue": null,
    "leasePercentage": null
  },
  {
    "templateName": "M4A1消音版 | 闪回 (崭新出厂)",
    "templateId": "47878",
    "iconUrl": "https://youpin.img898.com/csgo/template/51c18d2d36c44f67a4b01b055e2c4ae4.png",
    "price": "¥1255",
    "leasePrice": null,
    "increasePercentage": null,
    "increaseValue": null,
    "leasePercentage": null
  },
  {
    "templateName": "沙漠之鹰 | 午夜凶匪 (崭新出厂)",
    "templateId": "45200",
    "iconUrl": "https://youpin.img898.com/csgo/template/d6fd3b936f784fc98aa0a8d887866e65.png",
    "price": "¥1322",
    "leasePrice": null,
    "increasePercentage": null,
    "increaseValue": null,
    "leasePercentage": null
  },
  {
    "templateName": "沙漠之鹰 | 钴蓝禁锢 (崭新出厂)",
    "templateId": "2117",
    "iconUrl": "https://youpin.img898.com/csgo/template/aded26e27b1a4798afdaa0d642daeb70.png",
    "price": "¥1265",
    "leasePrice": null,
    "increasePercentage": null,
    "increaseValue": null,
    "leasePercentage": null
  },
  {
    "templateName": "M4A4 | 喧嚣杀戮 (久经沙场)",
    "templateId": "220",
    "iconUrl": "https://youpin.img898.com/csgo/template/6bb3d7ec186644ffbec17a4e6bf9f7f7.png",
    "price": "¥2498",
    "leasePrice": null,
    "increasePercentage": null,
    "increaseValue": null,
    "leasePercentage": null
  },
  {
    "templateName": "M4A4 | 合纵 (略有磨损)",
    "templateId": "61691",
    "iconUrl": "https://youpin.img898.com/csgo/template/0e895927c3a34f4f93607042085bdffa.png",
    "price": "¥4997",
    "leasePrice": null,
    "increasePercentage": null,
    "increaseValue": null,
    "leasePercentage": null
  },
  {
    "templateName": "格洛克 18 型 | 伽玛多普勒 (崭新出厂)",
    "templateId": "61735",
    "iconUrl": "https://youpin.img898.com/csgo/template/de443dc2daf445f3b61ced5be347770c.png",
    "price": "¥1090",
    "leasePrice": null,
    "increasePercentage": null,
    "increaseValue": null,
    "leasePercentage": null
  },
  {
    "templateName": "M4A4 | 喧嚣杀戮 (崭新出厂)",
    "templateId": "3320",
    "iconUrl": "https://youpin.img898.com/csgo/template/48b92c894f414becbd758a5d097fa5f3.png",
    "price": "¥5140",
    "leasePrice": null,
    "increasePercentage": null,
    "increaseValue": null,
    "leasePercentage": null
  },
  {
    "templateName": "M4A1消音版 | 印花集 (久经沙场)",
    "templateId": "34833",
    "iconUrl": "https://youpin.img898.com/csgo/template/7230fb6ec4f94dd2baa1ac97145dbcd9.png",
    "price": "¥1286",
    "leasePrice": null,
    "increasePercentage": null,
    "increaseValue": null,
    "leasePercentage": null
  },
  {
    "templateName": "M4A4 | 喧嚣杀戮 (略有磨损)",
    "templateId": "1229",
    "iconUrl": "https://youpin.img898.com/csgo/template/4d06be58fd9446d58508309c1363f07b.png",
    "price": "¥3060",
    "leasePrice": null,
    "increasePercentage": null,
    "increaseValue": null,
    "leasePercentage": null
  },
  {
    "templateName": "M4A4 | 合纵 (久经沙场)",
    "templateId": "61688",
    "iconUrl": "https://youpin.img898.com/csgo/template/89194fb0bf5b4e719acd35803f78082f.png",
    "price": "¥3999",
    "leasePrice": null,
    "increasePercentage": null,
    "increaseValue": null,
    "leasePercentage": null
  },
  {
    "templateName": "格洛克 18 型 | 大金牙 (崭新出厂)",
    "templateId": "109929",
    "iconUrl": "https://youpin.img898.com/csgo/template/d3be8d1929314d9190200d4b22a55c8b.png",
    "price": "¥2009.5",
    "leasePrice": null,
    "increasePercentage": null,
    "increaseValue": null,
    "leasePercentage": null
  },
  {
    "templateName": "M4A1消音版 | 印花集 (略有磨损)",
    "templateId": "10102",
    "iconUrl": "https://youpin.img898.com/csgo/template/bccd3b8aca6d4da8ab65784c9995306b.png",
    "price": "¥1899",
    "leasePrice": null,
    "increasePercentage": null,
    "increaseValue": null,
    "leasePercentage": null
  },
  {
    "templateName": "M4A4 | 狮鹫 (崭新出厂)",
    "templateId": "44835",
    "iconUrl": "https://youpin.img898.com/csgo/template/2fdbfcb1cbef467792c30bb0993bc308.png",
    "price": "¥1360",
    "leasePrice": null,
    "increasePercentage": null,
    "increaseValue": null,
    "leasePercentage": null
  },
  {
    "templateName": "骷髅匕首（★）",
    "templateId": "44661",
    "iconUrl": "https://youpin.img898.com/csgo/template/fd07716f85454eafb0ec09ca9e1757a7.png",
    "price": "¥1717",
    "leasePrice": null,
    "increasePercentage": null,
    "increaseValue": null,
    "leasePercentage": null
  },
  {
    "templateName": "M9 刺刀（★） | 多普勒 (崭新出厂)",
    "templateId": "754",
    "iconUrl": "https://youpin.img898.com/csgo/template/04755e24096640f89f3dcc96ab6f01ce.png",
    "price": "¥6243",
    "leasePrice": null,
    "increasePercentage": null,
    "increaseValue": null,
    "leasePercentage": null
  },
  {
    "templateName": "M4A4 | 地狱烈焰 (崭新出厂)",
    "templateId": "43649",
    "iconUrl": "https://youpin.img898.com/csgo/template/b2fadaec3a8e4f24a2c3637e65321e6d.png",
    "price": "¥3850",
    "leasePrice": null,
    "increasePercentage": null,
    "increaseValue": null,
    "leasePercentage": null
  },
  {
    "templateName": "SSG 08 | 炎龙之焰 (久经沙场)",
    "templateId": "2004",
    "iconUrl": "https://youpin.img898.com/csgo/template/b1009eaf82004b369a04f2011319845c.png",
    "price": "¥2178",
    "leasePrice": null,
    "increasePercentage": null,
    "increaseValue": null,
    "leasePercentage": null
  },
  {
    "templateName": "M4A4 | X 射线 (崭新出厂)",
    "templateId": "2739",
    "iconUrl": "https://youpin.img898.com/csgo/template/72c99292c36b4d97ba494f7964dfd6ce.png",
    "price": "¥1840",
    "leasePrice": null,
    "increasePercentage": null,
    "increaseValue": null,
    "leasePercentage": null
  },
  {
    "templateName": "AK-47 | 血腥运动 (略有磨损)",
    "templateId": "1572",
    "iconUrl": "https://youpin.img898.com/csgo/template/2dbe70d562cc4015b59ed7ee52bca500.png",
    "price": "¥1004",
    "leasePrice": null,
    "increasePercentage": null,
    "increaseValue": null,
    "leasePercentage": null
  },
  {
    "templateName": "蝴蝶刀（★） | 伽玛多普勒 (崭新出厂)",
    "templateId": "62272",
    "iconUrl": "https://youpin.img898.com/csgo/template/134057d62fc54aedac814515f2cb87a3.png",
    "price": "¥12265.5",
    "leasePrice": null,
    "increasePercentage": null,
    "increaseValue": null,
    "leasePercentage": null
  },
  {
    "templateName": "沙漠之鹰 | 沙漠之狐 (崭新出厂)",
    "templateId": "61660",
    "iconUrl": "https://youpin.img898.com/csgo/template/81a1dacac5a54e67be425f3ddd951fec.png",
    "price": "¥3598.5",
    "leasePrice": null,
    "increasePercentage": null,
    "increaseValue": null,
    "leasePercentage": null
  },
  {
    "templateName": "M4A1消音版 | 控制台 (崭新出厂)",
    "templateId": "46886",
    "iconUrl": "https://youpin.img898.com/csgo/template/70f73fa3614c4c5789cd8465e9c97098.png",
    "price": "¥1529.5",
    "leasePrice": null,
    "increasePercentage": null,
    "increaseValue": null,
    "leasePercentage": null
  },
  {
    "templateName": "血猎手套（★） | 蛇咬 (久经沙场)",
    "templateId": "47111",
    "iconUrl": "https://youpin.img898.com/csgo/template/96fb621e18e24b779d636f9898111b83.png",
    "price": "¥2015",
    "leasePrice": null,
    "increasePercentage": null,
    "increaseValue": null,
    "leasePercentage": null
  },
  {
    "templateName": "AWP | 石墨黑 (崭新出厂)",
    "templateId": "1242",
    "iconUrl": "https://youpin.img898.com/csgo/template/d6c5fa00ceca40d987044b6d9cb049f5.png",
    "price": "¥1718.18",
    "leasePrice": null,
    "increasePercentage": null,
    "increaseValue": null,
    "leasePercentage": null
  },
  {
    "templateName": "运动手套（★） | 弹弓 (久经沙场)",
    "templateId": "46887",
    "iconUrl": "https://youpin.img898.com/csgo/template/b83e93643c7d4790bc76419da27e40a6.png",
    "price": "¥2565",
    "leasePrice": null,
    "increasePercentage": null,
    "increaseValue": null,
    "leasePercentage": null
  },
  {
    "templateName": "蝴蝶刀（★） | 自动化 (久经沙场)",
    "templateId": "62035",
    "iconUrl": "https://youpin.img898.com/csgo/template/3e23d5301477455f8e647de2f679bf54.png",
    "price": "¥5644",
    "leasePrice": null,
    "increasePercentage": null,
    "increaseValue": null,
    "leasePercentage": null
  },
  {
    "templateName": "摩托手套（★） | 清凉薄荷 (久经沙场)",
    "templateId": "2140",
    "iconUrl": "https://youpin.img898.com/csgo/template/4986bba7a30647068b4310eb622aede7.png",
    "price": "¥13438.5",
    "leasePrice": null,
    "increasePercentage": null,
    "increaseValue": null,
    "leasePercentage": null
  },
  {
    "templateName": "专业手套（★） | 翠绿之网 (久经沙场)",
    "templateId": "13167",
    "iconUrl": "https://youpin.img898.com/csgo/template/8d70e7b3f5e24a7b9a5c7259942f785a.png",
    "price": "¥13299.5",
    "leasePrice": null,
    "increasePercentage": null,
    "increaseValue": null,
    "leasePercentage": null
  },
  {
    "templateName": "运动手套（★） | 树篱迷宫 (久经沙场)",
    "templateId": "13177",
    "iconUrl": "https://youpin.img898.com/csgo/template/f9ecb43ae10540148a5733e4de9b72b9.png",
    "price": "¥34987.5",
    "leasePrice": null,
    "increasePercentage": null,
    "increaseValue": null,
    "leasePercentage": null
  },
  {
    "templateName": "爪子刀（★） | 伽玛多普勒 (崭新出厂)",
    "templateId": "43529",
    "iconUrl": "https://youpin.img898.com/csgo/template/023246c560934022a7bae4003f3de6a8.png",
    "price": "¥11100",
    "leasePrice": null,
    "increasePercentage": null,
    "increaseValue": null,
    "leasePercentage": null
  },
  {
    "templateName": "运动手套（★） | 干旱 (久经沙场)",
    "templateId": "2781",
    "iconUrl": "https://youpin.img898.com/csgo/template/75adf726bfe4454ab9eadc024a211322.png",
    "price": "¥10694.5",
    "leasePrice": null,
    "increasePercentage": null,
    "increaseValue": null,
    "leasePercentage": null
  },
  {
    "templateName": "蝴蝶刀（★） | 多普勒 (崭新出厂)",
    "templateId": "45985",
    "iconUrl": "https://youpin.img898.com/csgo/template/2ceba4bb206d45b3a143eeaac707a187.png",
    "price": "¥13480.5",
    "leasePrice": null,
    "increasePercentage": null,
    "increaseValue": null,
    "leasePercentage": null
  },
  {
    "templateName": "驾驶手套（★） | 深红织物 (久经沙场)",
    "templateId": "2744",
    "iconUrl": "https://youpin.img898.com/csgo/template/e31a8ae14ebe41ffa271ff2f15552afa.png",
    "price": "¥13700",
    "leasePrice": null,
    "increasePercentage": null,
    "increaseValue": null,
    "leasePercentage": null
  },
  {
    "templateName": "摩托手套（★） | 薄荷 (久经沙场)",
    "templateId": "5000",
    "iconUrl": "https://youpin.img898.com/csgo/template/8a0217c52be042468385f29782d9a098.png",
    "price": "¥19998",
    "leasePrice": null,
    "increasePercentage": null,
    "increaseValue": null,
    "leasePercentage": null
  },
  {
    "templateName": "蝴蝶刀（★） | 渐变之色 (崭新出厂)",
    "templateId": "1980",
    "iconUrl": "https://youpin.img898.com/csgo/template/dac8ae4a855d4b1fb2867f0f5e8629e7.png",
    "price": "¥14199.5",
    "leasePrice": null,
    "increasePercentage": null,
    "increaseValue": null,
    "leasePercentage": null
  },
  {
    "templateName": "摩托手套（★） | 清凉薄荷 (略有磨损)",
    "templateId": "52711",
    "iconUrl": "https://youpin.img898.com/csgo/template/698bd78841724156bc5f4c6771b3b4b3.png",
    "price": "¥14400",
    "leasePrice": null,
    "increasePercentage": null,
    "increaseValue": null,
    "leasePercentage": null
  },
  {
    "templateName": "M4A4 | 合纵 (崭新出厂)",
    "templateId": "61689",
    "iconUrl": "https://youpin.img898.com/csgo/template/310cbadb61b24b18a23b23926c9cfa28.png",
    "price": "¥12788",
    "leasePrice": null,
    "increasePercentage": null,
    "increaseValue": null,
    "leasePercentage": null
  },
  {
    "templateName": "专业手套（★） | 翠绿之网 (略有磨损)",
    "templateId": "45307",
    "iconUrl": "https://youpin.img898.com/csgo/template/352d574574d8439d81d931916837c4ba.png",
    "price": "¥15300",
    "leasePrice": null,
    "increasePercentage": null,
    "increaseValue": null,
    "leasePercentage": null
  },
  {
    "templateName": "运动手套（★） | 超导体 (久经沙场)",
    "templateId": "44280",
    "iconUrl": "https://youpin.img898.com/csgo/template/d257398485164bd0bf077ca1ac684854.png",
    "price": "¥15599.5",
    "leasePrice": null,
    "increasePercentage": null,
    "increaseValue": null,
    "leasePercentage": null
  },
  {
    "templateName": "格洛克 18 型 | 渐变之色 (崭新出厂)",
    "templateId": "50998",
    "iconUrl": "https://youpin.img898.com/csgo/template/7fb6872d50cc4ad6b84bb42d724515c3.png",
    "price": "¥11338.5",
    "leasePrice": null,
    "increasePercentage": null,
    "increaseValue": null,
    "leasePercentage": null
  },
  {
    "templateName": "爪子刀（★） | 渐变之色 (崭新出厂)",
    "templateId": "47033",
    "iconUrl": "https://youpin.img898.com/csgo/template/834c2fc2710f4da794a95c8d64072640.png",
    "price": "¥12370",
    "leasePrice": null,
    "increasePercentage": null,
    "increaseValue": null,
    "leasePercentage": null
  },
  {
    "templateName": "M4A1消音版 | 赤红新星 (崭新出厂)",
    "templateId": "47839",
    "iconUrl": "https://youpin.img898.com/csgo/template/828c98fb429f4e408ac023e903029dc2.png",
    "price": "¥12300",
    "leasePrice": null,
    "increasePercentage": null,
    "increaseValue": null,
    "leasePercentage": null
  },
  {
    "templateName": "AK-47 | X 射线 (崭新出厂)",
    "templateId": "47261",
    "iconUrl": "https://youpin.img898.com/csgo/template/286f1d20d26b42f384f07ec5b0b17eea.png",
    "price": "¥17199",
    "leasePrice": null,
    "increasePercentage": null,
    "increaseValue": null,
    "leasePercentage": null
  },
  {
    "templateName": "专业手套（★） | 深红和服 (久经沙场)",
    "templateId": "46476",
    "iconUrl": "https://youpin.img898.com/csgo/template/077ecfb6137f4296a6f56cfb13b9491b.png",
    "price": "¥12000",
    "leasePrice": null,
    "increasePercentage": null,
    "increaseValue": null,
    "leasePercentage": null
  },
  {
    "templateName": "AWP | 巨龙传说 (崭新出厂)",
    "templateId": "49056",
    "iconUrl": "https://youpin.img898.com/csgo/template/449aba4b0de84ccb876562cedce83ee6.png",
    "price": "¥75400",
    "leasePrice": null,
    "increasePercentage": null,
    "increaseValue": null,
    "leasePercentage": null
  },
  {
    "templateName": "运动手套（★） | 潘多拉之盒 (破损不堪)",
    "templateId": "45918",
    "iconUrl": "https://youpin.img898.com/csgo/template/6a56c96669424dcda2dd94c9d971413c.png",
    "price": "¥22222",
    "leasePrice": null,
    "increasePercentage": null,
    "increaseValue": null,
    "leasePercentage": null
  },
  {
    "templateName": "M4A1消音版 | 紧迫危机",
    "templateId": "62276",
    "iconUrl": "https://youpin.img898.com/csgo/template/699e305d5aaf479285cbeecb026ce6b7.png",
    "price": "¥10500",
    "leasePrice": null,
    "increasePercentage": null,
    "increaseValue": null,
    "leasePercentage": null
  },
  {
    "templateName": "AK-47 | 水栽竹 (崭新出厂)",
    "templateId": "43800",
    "iconUrl": "https://youpin.img898.com/csgo/template/ca3e127fd6c74f309d21722aa0d626fd.png",
    "price": "¥35000",
    "leasePrice": null,
    "increasePercentage": null,
    "increaseValue": null,
    "leasePercentage": null
  },
  {
    "templateName": "驾驶手套（★） | 深红织物 (略有磨损)",
    "templateId": "53026",
    "iconUrl": "https://youpin.img898.com/csgo/template/3710f1fd6f5a4ee4b5bfdd5b0420e2e2.png",
    "price": "¥14888",
    "leasePrice": null,
    "increasePercentage": null,
    "increaseValue": null,
    "leasePercentage": null
  },
  {
    "templateName": "M4A4 | 波塞冬 (崭新出厂)",
    "templateId": "2128",
    "iconUrl": "https://youpin.img898.com/csgo/template/087671221f27454c95533116ed7d202c.png",
    "price": "¥13000",
    "leasePrice": null,
    "increasePercentage": null,
    "increaseValue": null,
    "leasePercentage": null
  },
  {
    "templateName": "专业手套（★） | 深红和服 (略有磨损)",
    "templateId": "49118",
    "iconUrl": "https://youpin.img898.com/csgo/template/46cffa7dee3b41a5af1dbca98921c409.png",
    "price": "¥17665.5",
    "leasePrice": null,
    "increasePercentage": null,
    "increaseValue": null,
    "leasePercentage": null
  },
  {
    "templateName": "运动手套（★） | 超导体 (略有磨损)",
    "templateId": "47524",
    "iconUrl": "https://youpin.img898.com/csgo/template/69179d70ff4f459885b40da2c8f794fd.png",
    "price": "¥21298",
    "leasePrice": null,
    "increasePercentage": null,
    "increaseValue": null,
    "leasePercentage": null
  },
  {
    "templateName": "运动手套（★） | 超导体 (破损不堪)",
    "templateId": "46479",
    "iconUrl": "https://youpin.img898.com/csgo/template/ba3951d146154c048b8f8455a27095e6.png",
    "price": "¥10300",
    "leasePrice": null,
    "increasePercentage": null,
    "increaseValue": null,
    "leasePercentage": null
  },
  {
    "templateName": "AWP | 永恒之枪 (崭新出厂)",
    "templateId": "48830",
    "iconUrl": "https://youpin.img898.com/csgo/template/6a150cbfa5d940079157d7f4ce416792.png",
    "price": "¥79000",
    "leasePrice": null,
    "increasePercentage": null,
    "increaseValue": null,
    "leasePercentage": null
  },
  {
    "templateName": "运动手套（★） | 潘多拉之盒 (略有磨损)",
    "templateId": "46300",
    "iconUrl": "https://youpin.img898.com/csgo/template/ee03c89942e946eaa18db99bb007aac7.png",
    "price": "¥38198.5",
    "leasePrice": null,
    "increasePercentage": null,
    "increaseValue": null,
    "leasePercentage": null
  }
]